sucks/__init__.py
sucks/cli.py
sucks-0.9.6.dist-info/LICENSE.txt
sucks-0.9.6.dist-info/METADATA
sucks-0.9.6.dist-info/WHEEL
sucks-0.9.6.dist-info/entry_points.txt
sucks-0.9.6.dist-info/top_level.txt
sucks-0.9.6.dist-info/RECORD
