Metadata-Version: 2.1
Name: sucks
Version: 0.9.6
Summary: an abandoned library for controlling certain robot vacuums
Home-page: https://github.com/wpietri/sucks
Author: William Pietri
Author-email: sucks-users@googlegroups.com
License: GPL-3.0
Keywords: home automation vacuum robot
Platform: UNKNOWN
Classifier: Development Status :: 4 - Beta
Classifier: Intended Audience :: Developers
Classifier: Topic :: Software Development :: Libraries
Classifier: Topic :: Home Automation
Classifier: License :: OSI Approved :: GNU General Public License v3 (GPLv3)
Classifier: Programming Language :: Python :: 3.5
Requires-Dist: sleekxmppfs (>=1.3.4)
Requires-Dist: click (>=6)
Requires-Dist: requests (>=2.18)
Requires-Dist: pycryptodome (>=3.4)
Requires-Dist: pycountry-convert (>=0.5)
Requires-Dist: stringcase (>=1.2)
Provides-Extra: dev
Requires-Dist: nose ; extra == 'dev'
Requires-Dist: requests-mock (>=1.3) ; extra == 'dev'
